pomodorotimer/__init__.py
pomodorotimer/graph_statistic.py
pomodorotimer/pomodorotimer.py
pomodorotimer/sound.py
pomodorotimer/statistics_db.py
pomodorotimer/stats.html
pomodorotimer/tic-tic.wav
pomodorotimer-0.2.4.dist-info/AUTHORS
pomodorotimer-0.2.4.dist-info/LICENSE
pomodorotimer-0.2.4.dist-info/METADATA
pomodorotimer-0.2.4.dist-info/WHEEL
pomodorotimer-0.2.4.dist-info/entry_points.txt
pomodorotimer-0.2.4.dist-info/top_level.txt
pomodorotimer-0.2.4.dist-info/RECORD
