Metadata-Version: 2.1
Name: pomodorotimer
Version: 0.2.4
Summary: CLI Pomodoro Timer
Home-page: https://github.com/patsuckow/pomodorotimer
Author: Alexey Patsukov 🇷🇺
Author-email: patsuckow@yandex.ru
License: GNU General Public License v3 (GPLv3)
Project-URL: Bug Tracker, https://github.com/patsuckow/pomodorotimer/issues
Project-URL: Donate, https://www.paypal.me/patsuckow
Keywords: pomodoro,tomato,pomodorotimer,pomodoro timer,pomodoro technique,productivity,time management,countdown,stopwatch,timer,eta,freelance,freelancing,CLI
Classifier: Development Status :: 4 - Beta
Classifier: Environment :: Console
Classifier: Operating System :: OS Independent
Classifier: Programming Language :: Python :: 3
Classifier: Intended Audience :: Developers
Classifier: Topic :: Utilities
Requires-Python: >=3.10.13
License-File: LICENSE
License-File: AUTHORS
Requires-Dist: pydub ==0.25.1
Requires-Dist: setuptools ==69.0.2
Requires-Dist: matplotlib ==3.8.2
Requires-Dist: sounddevice ==0.4.6
Requires-Dist: numpy ==1.26.2
Requires-Dist: scipy ==1.11.4
